imagedeck/__init__.py
imagedeck/admin.py
imagedeck/apps.py
imagedeck/management/commands/imagedeck_combine.py
imagedeck/management/commands/imagedeck_generate.py
imagedeck/management/commands/imagedeck_glob.py
imagedeck/migrations/0001_initial.py
imagedeck/migrations/0002_auto_20201102_1443.py
imagedeck/migrations/0003_deckbase_images.py
imagedeck/migrations/0004_auto_20201102_1538.py
imagedeck/migrations/0005_auto_20201102_1555.py
imagedeck/migrations/0006_deckmembership_primary.py
imagedeck/migrations/0007_auto_20201103_0931.py
imagedeck/migrations/0008_deckimagefiler.py
imagedeck/migrations/0009_auto_20201122_2300.py
imagedeck/migrations/0010_deckiiif.py
imagedeck/migrations/0011_auto_20210901_1642.py
imagedeck/migrations/__init__.py
imagedeck/models.py
imagedeck/settings.py
imagedeck/static/imagedeck/vendor/jquery-file-upload/jquery.fileupload.js
imagedeck/static/imagedeck/vendor/jquery-file-upload/jquery.iframe-transport.js
imagedeck/static/imagedeck/vendor/jquery.ui.widget.js
imagedeck/templatetags/__init__.py
imagedeck/templatetags/imagedeck.py
imagedeck/urls.py
imagedeck/util.py
imagedeck/views.py
django_imagedeck-0.3.3.dist-info/LICENSE
django_imagedeck-0.3.3.dist-info/WHEEL
django_imagedeck-0.3.3.dist-info/METADATA
django_imagedeck-0.3.3.dist-info/RECORD
